streamish/__init__.py
streamish/_util.py
streamish/stream.py
streamish/ops/__init__.py
streamish/ops/combine.py
streamish/ops/filter.py
streamish/ops/group.py
streamish/ops/transform.py
streamish-0.1.3.dist-info/METADATA
streamish-0.1.3.dist-info/WHEEL
streamish-0.1.3.dist-info/licenses/LICENSE
streamish-0.1.3.dist-info/RECORD
