Metadata-Version: 2.4
Name: streamish
Version: 0.1.3
Summary: Iterator and async iterator utilities for Python
Project-URL: Homepage, https://github.com/gabfssilva/streamish
Project-URL: Repository, https://github.com/gabfssilva/streamish
Author: Gabriel Francisco
License-Expression: MIT
License-File: LICENSE
Keywords: async,functional,iterator,pipeline,stream
Classifier: Development Status :: 4 - Beta
Classifier: Intended Audience :: Developers
Classifier: License :: OSI Approved :: MIT License
Classifier: Programming Language :: Python :: 3
Classifier: Programming Language :: Python :: 3.12
Classifier: Programming Language :: Python :: 3.13
Classifier: Programming Language :: Python :: 3.14
Classifier: Typing :: Typed
Requires-Python: >=3.12
